securex/__init__.py
py_secure-0.0.3.dist-info/LICENSE.txt
py_secure-0.0.3.dist-info/METADATA
py_secure-0.0.3.dist-info/WHEEL
py_secure-0.0.3.dist-info/top_level.txt
py_secure-0.0.3.dist-info/RECORD
