Metadata-Version: 2.1
Name: py-secure
Version: 0.0.3
Summary: SECURITY IS BEST
Home-page: https://github.com/LEGENDXOP
Author: LEGENDX22
Author-email: legendxx08377@gmail.com
License: UNKNOWN
Platform: UNKNOWN
Classifier: Programming Language :: Python :: 3
Classifier: License :: OSI Approved :: MIT License
Classifier: Operating System :: OS Independent
